pwhois
setup.py
pythonwhois/__init__.py
pythonwhois/airports.dat
pythonwhois/countries.dat
pythonwhois/countries3.dat
pythonwhois/net.py
pythonwhois/parse.py
pythonwhois/shared.py
pythonwhois/states_au.dat
pythonwhois/states_ca.dat
pythonwhois/states_us.dat
sb2w_pythonwhois.egg-info/PKG-INFO
sb2w_pythonwhois.egg-info/SOURCES.txt
sb2w_pythonwhois.egg-info/dependency_links.txt
sb2w_pythonwhois.egg-info/requires.txt
sb2w_pythonwhois.egg-info/top_level.txt