Metadata-Version: 1.1
Name: sb2w-pythonwhois
Version: 2.4.3
Summary: Temporary Fork - the original project is `http://cryto.net/pythonwhois` Module for retrieving and parsing the WHOIS data for a domain. Supports most domains. No dependencies.
Home-page: https://github.com/siteblindado/python-whois
Author: siteblindado
Author-email: account.dev@siteblindado.com.br
License: WTFPL
Platform: UNKNOWN
Provides: pythonwhois
